functions_by_nasiba_87/math_functions.py
functions_by_nasiba_87-0.3.0.dist-info/WHEEL
functions_by_nasiba_87-0.3.0.dist-info/METADATA
functions_by_nasiba_87-0.3.0.dist-info/RECORD
