Metadata-Version: 2.1
Name: functions-by-nasiba-87
Version: 0.3.0
Summary: 
Author: somename
Author-email: a@gmail.com
Requires-Python: >=3.10,<4.0
Classifier: Programming Language :: Python :: 3
Classifier: Programming Language :: Python :: 3.10
Classifier: Programming Language :: Python :: 3.11
